HowtodoinjavaJavaJiaochengChuyiFix1/README.md
HowtodoinjavaJavaJiaochengChuyiFix1/__init__.py
HowtodoinjavaJavaJiaochengChuyiFix1/__main__.py
HowtodoinjavaJavaJiaochengChuyiFix1/file.epub
HowtodoinjavaJavaJiaochengChuyiFix1/index.html
HowtodoinjavaJavaJiaochengChuyiFix1/css/__init__.py
HowtodoinjavaJavaJiaochengChuyiFix1/css/annotations.css
HowtodoinjavaJavaJiaochengChuyiFix1/css/main.css
HowtodoinjavaJavaJiaochengChuyiFix1/css/normalize.css
HowtodoinjavaJavaJiaochengChuyiFix1/css/popup.css
HowtodoinjavaJavaJiaochengChuyiFix1/font/__init__.py
HowtodoinjavaJavaJiaochengChuyiFix1/font/fontello.eot
HowtodoinjavaJavaJiaochengChuyiFix1/font/fontello.svg
HowtodoinjavaJavaJiaochengChuyiFix1/font/fontello.ttf
HowtodoinjavaJavaJiaochengChuyiFix1/font/fontello.woff
HowtodoinjavaJavaJiaochengChuyiFix1/img/__init__.py
HowtodoinjavaJavaJiaochengChuyiFix1/img/annotator-glyph-sprite.png
HowtodoinjavaJavaJiaochengChuyiFix1/img/annotator-icon-sprite.png
HowtodoinjavaJavaJiaochengChuyiFix1/img/apple-touch-icon.png
HowtodoinjavaJavaJiaochengChuyiFix1/img/cancelfullscreen.png
HowtodoinjavaJavaJiaochengChuyiFix1/img/close.png
HowtodoinjavaJavaJiaochengChuyiFix1/img/fullscreen.png
HowtodoinjavaJavaJiaochengChuyiFix1/img/loader.gif
HowtodoinjavaJavaJiaochengChuyiFix1/img/menu-icon.png
HowtodoinjavaJavaJiaochengChuyiFix1/img/save.png
HowtodoinjavaJavaJiaochengChuyiFix1/img/saved.png
HowtodoinjavaJavaJiaochengChuyiFix1/img/settings-s.png
HowtodoinjavaJavaJiaochengChuyiFix1/img/settings.png
HowtodoinjavaJavaJiaochengChuyiFix1/img/star.png
HowtodoinjavaJavaJiaochengChuyiFix1/js/__init__.py
HowtodoinjavaJavaJiaochengChuyiFix1/js/epub.js
HowtodoinjavaJavaJiaochengChuyiFix1/js/epub.min.js
HowtodoinjavaJavaJiaochengChuyiFix1/js/epub.min.map
HowtodoinjavaJavaJiaochengChuyiFix1/js/hooks.min.js
HowtodoinjavaJavaJiaochengChuyiFix1/js/hooks.min.map
HowtodoinjavaJavaJiaochengChuyiFix1/js/reader.js
HowtodoinjavaJavaJiaochengChuyiFix1/js/reader.js.map
HowtodoinjavaJavaJiaochengChuyiFix1/js/reader.min.js
howtodoinjava_java_jiaocheng_chuyi_fix1-2025.3.24.1.dist-info/METADATA
howtodoinjava_java_jiaocheng_chuyi_fix1-2025.3.24.1.dist-info/WHEEL
howtodoinjava_java_jiaocheng_chuyi_fix1-2025.3.24.1.dist-info/entry_points.txt
howtodoinjava_java_jiaocheng_chuyi_fix1-2025.3.24.1.dist-info/top_level.txt
howtodoinjava_java_jiaocheng_chuyi_fix1-2025.3.24.1.dist-info/RECORD
